src/__init__.py
src/__main__.py
src/cache.py
src/client.py
src/config.py
src/errors.py
src/server.py
mcp_4get-0.1.2.dist-info/WHEEL
mcp_4get-0.1.2.dist-info/entry_points.txt
mcp_4get-0.1.2.dist-info/METADATA
mcp_4get-0.1.2.dist-info/RECORD
