Metadata-Version: 2.3
Name: mcp-4get
Version: 0.1.2
Summary: An MCP server for 4get search engine
Requires-Dist: fastmcp>=2.12.3
Requires-Python: >=3.13
